iwdgui/__init__.py
iwdgui/__main__.py
iwdgui/ap_frame.py
iwdgui/comboboxtext.py
iwdgui/common_frame.py
iwdgui/dbus.py
iwdgui/entry.py
iwdgui/exitcodes.py
iwdgui/icon.py
iwdgui/interface_frame.py
iwdgui/iwdgui.py
iwdgui/known_nws_frame.py
iwdgui/menu.py
iwdgui/msg_window.py
iwdgui/notify.py
iwdgui/nw_addr.py
iwdgui/offline_frame.py
iwdgui/profile_store.py
iwdgui/pyiwd.py
iwdgui/station_frame.py
iwdgui/wifi.py
iwdgui-0.3.0.data/data/share/applications/iwdgui.desktop
iwdgui-0.3.0.data/data/share/icons/hicolor/48x48/apps/iwdgui.png
iwdgui-0.3.0.data/data/share/icons/hicolor/96x96/apps/iwdgui.png
iwdgui-0.3.0.dist-info/LICENSE
iwdgui-0.3.0.dist-info/METADATA
iwdgui-0.3.0.dist-info/WHEEL
iwdgui-0.3.0.dist-info/entry_points.txt
iwdgui-0.3.0.dist-info/top_level.txt
iwdgui-0.3.0.dist-info/RECORD
