Metadata-Version: 2.1
Name: iwdgui
Version: 0.3.0
Summary: A graphical frontend for IWD, Intel's iNet Wireless Daemon
Home-page: https://gitlab.com/hfernh/iwdgui
Author: Johannes Willem Fernhout
Author-email: hfern@fernhout.info
License: BSD-3-Clause
Keywords: wireless,networking,wifi,iwd,graphical,gtk
Platform: Linux
Classifier: Development Status :: 4 - Beta
Classifier: License :: OSI Approved :: BSD License
Classifier: Operating System :: POSIX
Classifier: Programming Language :: Python
Classifier: Programming Language :: Python :: 3 :: Only
Classifier: Programming Language :: Python :: 3.10
Classifier: Programming Language :: Python :: 3.11
Classifier: Intended Audience :: End Users/Desktop
Classifier: Environment :: X11 Applications :: GTK
Classifier: Topic :: System :: Networking
Classifier: Topic :: Utilities
Requires-Python: >=3.10
License-File: LICENSE
